{
    "key": "group_66e972a25089c",
    "title": "Options - Éléments récurrents",
    "fields": [
        {
            "key": "field_66e972a392216",
            "label": "Grille de logo \"Ils nous font confiance\"",
            "name": "",
            "aria-label": "",
            "type": "tab",
            "instructions": "",
            "required": 0,
            "conditional_logic": 0,
            "wrapper": {
                "width": "",
                "class": "",
                "id": ""
            },
            "placement": "left",
            "endpoint": 0,
            "selected": 0
        },
        {
            "key": "field_66e973f592217",
            "label": "Où est-ce que cet élément apparaît ?",
            "name": "",
            "aria-label": "",
            "type": "message",
            "instructions": "",
            "required": 0,
            "conditional_logic": 0,
            "wrapper": {
                "width": "",
                "class": "",
                "id": ""
            },
            "message": "Apparaît sur la page d'accueil et la page Notre écosystème.",
            "new_lines": "wpautop",
            "esc_html": 0
        },
        {
            "key": "field_66e974729f780",
            "label": "Titre de l'élément",
            "name": "partners_grid_title",
            "aria-label": "",
            "type": "text",
            "instructions": "",
            "required": 1,
            "conditional_logic": 0,
            "wrapper": {
                "width": "",
                "class": "",
                "id": ""
            },
            "default_value": "",
            "maxlength": "",
            "allow_in_bindings": 0,
            "placeholder": "",
            "prepend": "",
            "append": ""
        },
        {
            "key": "field_66e9749f9f781",
            "label": "Texte de l'élément",
            "name": "partners_grid_text",
            "aria-label": "",
            "type": "wysiwyg",
            "instructions": "Les sauts à la ligne sont pris en compte.",
            "required": 1,
            "conditional_logic": 0,
            "wrapper": {
                "width": "",
                "class": "",
                "id": ""
            },
            "default_value": "",
            "allow_in_bindings": 0,
            "tabs": "all",
            "toolbar": "basic",
            "media_upload": 0,
            "delay": 1
        },
        {
            "key": "field_66e97527896b9",
            "label": "Logos des partenaires",
            "name": "partners_grid_logos",
            "aria-label": "",
            "type": "gallery",
            "instructions": "Il est préférable d'utiliser des images sans fond blanc, afin que celui-ci n'apparaisse pas sur la page. Vous pouvez également réorganiser les images dans l'ordre souhaité.",
            "required": 1,
            "conditional_logic": 0,
            "wrapper": {
                "width": "",
                "class": "",
                "id": ""
            },
            "return_format": "array",
            "library": "all",
            "min": "",
            "max": "",
            "min_width": "",
            "min_height": "",
            "min_size": "",
            "max_width": "",
            "max_height": "",
            "max_size": "",
            "mime_types": "png, svg, webp",
            "insert": "append",
            "preview_size": "thumbnail"
        }
    ],
    "location": [
        [
            {
                "param": "options_page",
                "operator": "==",
                "value": "options"
            }
        ]
    ],
    "menu_order": 3,
    "position": "normal",
    "style": "default",
    "label_placement": "top",
    "instruction_placement": "label",
    "hide_on_screen": "",
    "active": true,
    "description": "",
    "show_in_rest": 0,
    "modified": 1726583125
}
